{
    "total": [
        {
            "id": "61550591979493",
            "count": 624
        },
        {
            "id": "61551750047010",
            "count": 0
        },
        {
            "id": "61553301081985",
            "count": 64
        },
        {
            "id": "100004843834867",
            "count": 14
        },
        {
            "id": "100007127623687",
            "count": 19
        },
        {
            "id": "100009474414028",
            "count": 862
        },
        {
            "id": "100011730017799",
            "count": 0
        },
        {
            "id": "100013615989007",
            "count": 37
        },
        {
            "id": "100014148825001",
            "count": 0
        },
        {
            "id": "100019665720378",
            "count": 57
        },
        {
            "id": "100022200258722",
            "count": 1
        },
        {
            "id": "100022876771042",
            "count": 10
        },
        {
            "id": "100024420073212",
            "count": 32
        },
        {
            "id": "100025347006654",
            "count": 225
        },
        {
            "id": "100029650151945",
            "count": 2
        },
        {
            "id": "100030293616399",
            "count": 146
        },
        {
            "id": "100030990391436",
            "count": 1
        },
        {
            "id": "100031689702149",
            "count": 3
        },
        {
            "id": "100034576779493",
            "count": 393
        },
        {
            "id": "100034922898150",
            "count": 215
        },
        {
            "id": "100035299548315",
            "count": 109
        },
        {
            "id": "100037783553426",
            "count": 44
        },
        {
            "id": "100038339124447",
            "count": 0
        },
        {
            "id": "100039137588507",
            "count": 19
        },
        {
            "id": "100040415021585",
            "count": 57
        },
        {
            "id": "100041010338202",
            "count": 4
        },
        {
            "id": "100041163427907",
            "count": 0
        },
        {
            "id": "100041447961345",
            "count": 0
        },
        {
            "id": "100045475484543",
            "count": 306
        },
        {
            "id": "100046384474794",
            "count": 159
        },
        {
            "id": "100049908011793",
            "count": 14
        },
        {
            "id": "100049952270280",
            "count": 0
        },
        {
            "id": "100050444104881",
            "count": 6
        },
        {
            "id": "100050985814465",
            "count": 5
        },
        {
            "id": "100053388225103",
            "count": 6
        },
        {
            "id": "100053713476328",
            "count": 81
        },
        {
            "id": "100054260715984",
            "count": 0
        },
        {
            "id": "100054591240240",
            "count": 2
        },
        {
            "id": "100055154154050",
            "count": 1088
        },
        {
            "id": "100057164243839",
            "count": 6
        },
        {
            "id": "100059650390794",
            "count": 1400
        },
        {
            "id": "100061609086598",
            "count": 0
        },
        {
            "id": "100062257991835",
            "count": 1
        },
        {
            "id": "100063330711799",
            "count": 343
        },
        {
            "id": "100063637074188",
            "count": 4
        },
        {
            "id": "100063708825168",
            "count": 0
        },
        {
            "id": "100066662293438",
            "count": 0
        },
        {
            "id": "100067124820668",
            "count": 91
        },
        {
            "id": "100067729713825",
            "count": 0
        },
        {
            "id": "100067803637752",
            "count": 13
        },
        {
            "id": "100067839890353",
            "count": 32
        },
        {
            "id": "100068478576359",
            "count": 87
        },
        {
            "id": "100068817998875",
            "count": 114
        },
        {
            "id": "100069764767683",
            "count": 6
        },
        {
            "id": "100070013348463",
            "count": 5
        },
        {
            "id": "100070104925304",
            "count": 15
        },
        {
            "id": "100070899521002",
            "count": 53
        },
        {
            "id": "100071303594615",
            "count": 0
        },
        {
            "id": "100071627507465",
            "count": 869
        },
        {
            "id": "100072034345452",
            "count": 81
        },
        {
            "id": "100072548933925",
            "count": 6
        },
        {
            "id": "100072883089785",
            "count": 1
        },
        {
            "id": "100072934636127",
            "count": 10
        },
        {
            "id": "100073127936844",
            "count": 0
        },
        {
            "id": "100073985167088",
            "count": 1
        },
        {
            "id": "100074278195157",
            "count": 20
        },
        {
            "id": "100074341920164",
            "count": 0
        },
        {
            "id": "100074524321875",
            "count": 54
        },
        {
            "id": "100075980175339",
            "count": 23
        },
        {
            "id": "100076399151586",
            "count": 3
        },
        {
            "id": "100076975642630",
            "count": 0
        },
        {
            "id": "100077509305730",
            "count": 4
        },
        {
            "id": "100077597024757",
            "count": 0
        },
        {
            "id": "100077639637264",
            "count": 1
        },
        {
            "id": "100077971004043",
            "count": 9
        },
        {
            "id": "100078681550289",
            "count": 5
        },
        {
            "id": "100079130371607",
            "count": 10
        },
        {
            "id": "100079876959448",
            "count": 19
        },
        {
            "id": "100080804560507",
            "count": 17
        },
        {
            "id": "100081002237761",
            "count": 0
        },
        {
            "id": "100081206510186",
            "count": 10
        },
        {
            "id": "100081443772674",
            "count": 6
        },
        {
            "id": "100082552884338",
            "count": 22
        },
        {
            "id": "100083022811644",
            "count": 4
        },
        {
            "id": "100083504825451",
            "count": 286
        },
        {
            "id": "100084012548620",
            "count": 20
        },
        {
            "id": "100084071196298",
            "count": 59
        },
        {
            "id": "100084235487772",
            "count": 195
        },
        {
            "id": "100084459207826",
            "count": 26
        },
        {
            "id": "100085264847000",
            "count": 7
        },
        {
            "id": "100087223377781",
            "count": 0
        },
        {
            "id": "100088003426784",
            "count": 7
        },
        {
            "id": "100089669455408",
            "count": 1
        },
        {
            "id": "100091841472833",
            "count": 4
        },
        {
            "id": "100091847290662",
            "count": 28
        },
        {
            "id": "100091905835858",
            "count": 81
        },
        {
            "id": "100092011181468",
            "count": 23
        },
        {
            "id": "100092203035367",
            "count": 0
        },
        {
            "id": "100094046882331",
            "count": 9
        },
        {
            "id": "100094262430488",
            "count": 0
        },
        {
            "id": "100094326087158",
            "count": 14
        },
        {
            "id": "100094365050149",
            "count": 205
        },
        {
            "id": "100094496576944",
            "count": 1089
        },
        {
            "id": "100095080567117",
            "count": 108
        },
        {
            "id": "100011620237069",
            "count": 15
        },
        {
            "id": "100084174456709",
            "count": 17
        },
        {
            "id": "100082529241487",
            "count": 56
        },
        {
            "id": "100046043931686",
            "count": 8
        },
        {
            "id": "100086997663423",
            "count": 364
        },
        {
            "id": "100094285270891",
            "count": 230
        },
        {
            "id": "100037712385256",
            "count": 12
        },
        {
            "id": "100047759311760",
            "count": 159
        },
        {
            "id": "100092716934305",
            "count": 18
        },
        {
            "id": "100064106005769",
            "count": 31
        },
        {
            "id": "100090737150315",
            "count": 41
        },
        {
            "id": "100023390842520",
            "count": 61
        },
        {
            "id": "100027933579703",
            "count": 100
        },
        {
            "id": "100093250460325",
            "count": 327
        },
        {
            "id": "100027377297534",
            "count": 10
        },
        {
            "id": "100060560316441",
            "count": 43
        },
        {
            "id": "61551633732896",
            "count": 6
        },
        {
            "id": "100095425306290",
            "count": 30
        },
        {
            "id": "100088486644888",
            "count": 3
        }
    ],
    "week": [
        {
            "id": "61550591979493",
            "count": 0,
            "name": "Ng퀋敲렬 d칯ng facebook"
        },
        {
            "id": "61551750047010",
            "count": 0,
            "name": "Ng퀋敲렬 d칯ng facebook"
        },
        {
            "id": "61553301081985",
            "count": 0,
            "name": "Ng퀋敲렬 d칯ng facebook"
        },
        {
            "id": "100004843834867",
            "count": 0,
            "name": "Ng퀋敲렬 d칯ng Facebook"
        },
        {
            "id": "100007127623687",
            "count": 0,
            "name": "Ng퀋敲렬 d칯ng facebook"
        },
        {
            "id": "100009474414028",
            "count": 0,
            "name": "Ng퀋敲렬 d칯ng facebook"
        },
        {
            "id": "100011730017799",
            "count": 0,
            "name": "Ng퀋敲렬 d칯ng facebook"
        },
        {
            "id": "100013615989007",
            "count": 0,
            "name": "Ng퀋敲렬 d칯ng facebook"
        },
        {
            "id": "100014148825001",
            "count": 0,
            "name": "Ng퀋敲렬 d칯ng facebook"
        },
        {
            "id": "100019665720378",
            "count": 0,
            "name": "Ng퀋敲렬 d칯ng facebook"
        },
        {
            "id": "100022200258722",
            "count": 0,
            "name": "Ng퀋敲렬 d칯ng facebook"
        },
        {
            "id": "100022876771042",
            "count": 0,
            "name": "Ng퀋敲렬 d칯ng facebook"
        },
        {
            "id": "100024420073212",
            "count": 0,
            "name": "Ng퀋敲렬 d칯ng facebook"
        },
        {
            "id": "100025347006654",
            "count": 0,
            "name": "Ng퀋敲렬 d칯ng facebook"
        },
        {
            "id": "100029650151945",
            "count": 0,
            "name": "Ng퀋敲렬 d칯ng facebook"
        },
        {
            "id": "100030293616399",
            "count": 0,
            "name": "Ng퀋敲렬 d칯ng facebook"
        },
        {
            "id": "100030990391436",
            "count": 0,
            "name": "Ng퀋敲렬 d칯ng facebook"
        },
        {
            "id": "100031689702149",
            "count": 0,
            "name": "Ng퀋敲렬 d칯ng facebook"
        },
        {
            "id": "100034576779493",
            "count": 0,
            "name": "Ng퀋敲렬 d칯ng facebook"
        },
        {
            "id": "100034922898150",
            "count": 0,
            "name": "Ng퀋敲렬 d칯ng facebook"
        },
        {
            "id": "100035299548315",
            "count": 0,
            "name": "Ng퀋敲렬 d칯ng facebook"
        },
        {
            "id": "100037783553426",
            "count": 0,
            "name": "Ng퀋敲렬 d칯ng facebook"
        },
        {
            "id": "100038339124447",
            "count": 0,
            "name": "Ng퀋敲렬 d칯ng facebook"
        },
        {
            "id": "100039137588507",
            "count": 0,
            "name": "Ng퀋敲렬 d칯ng facebook"
        },
        {
            "id": "100040415021585",
            "count": 0,
            "name": "Ng퀋敲렬 d칯ng facebook"
        },
        {
            "id": "100041010338202",
            "count": 0,
            "name": "Ng퀋敲렬 d칯ng facebook"
        },
        {
            "id": "100041163427907",
            "count": 0,
            "name": "Ng퀋敲렬 d칯ng facebook"
        },
        {
            "id": "100041447961345",
            "count": 0,
            "name": "Ng퀋敲렬 d칯ng facebook"
        },
        {
            "id": "100045475484543",
            "count": 0,
            "name": "Ng퀋敲렬 d칯ng facebook"
        },
        {
            "id": "100046384474794",
            "count": 0,
            "name": "P. Hi故쯧"
        },
        {
            "id": "100049908011793",
            "count": 0,
            "name": "Ng퀋敲렬 d칯ng facebook"
        },
        {
            "id": "100049952270280",
            "count": 0,
            "name": "Ng퀋敲렬 d칯ng facebook"
        },
        {
            "id": "100050444104881",
            "count": 0,
            "name": "Ng퀋敲렬 d칯ng facebook"
        },
        {
            "id": "100050985814465",
            "count": 0,
            "name": "Ng퀋敲렬 d칯ng facebook"
        },
        {
            "id": "100053388225103",
            "count": 0,
            "name": "Ng퀋敲렬 d칯ng facebook"
        },
        {
            "id": "100053713476328",
            "count": 0,
            "name": "Ng퀋敲렬 d칯ng facebook"
        },
        {
            "id": "100054260715984",
            "count": 0,
            "name": "Ng퀋敲렬 d칯ng facebook"
        },
        {
            "id": "100054591240240",
            "count": 0,
            "name": "Ng퀋敲렬 d칯ng facebook"
        },
        {
            "id": "100055154154050",
            "count": 0,
            "name": "V칫 N-캠캒ng"
        },
        {
            "id": "100057164243839",
            "count": 0,
            "name": "Ng퀋敲렬 d칯ng facebook"
        },
        {
            "id": "100059650390794",
            "count": 0,
            "name": "Ng퀋敲렬 d칯ng facebook"
        },
        {
            "id": "100061609086598",
            "count": 0,
            "name": "Ng퀋敲렬 d칯ng facebook"
        },
        {
            "id": "100062257991835",
            "count": 0,
            "name": "Ng퀋敲렬 d칯ng facebook"
        },
        {
            "id": "100063330711799",
            "count": 0,
            "name": "Ng퀋敲렬 d칯ng facebook"
        },
        {
            "id": "100063637074188",
            "count": 0,
            "name": "Ng퀋敲렬 d칯ng facebook"
        },
        {
            "id": "100063708825168",
            "count": 0,
            "name": "Ng퀋敲렬 d칯ng facebook"
        },
        {
            "id": "100066662293438",
            "count": 0,
            "name": "Ng퀋敲렬 d칯ng facebook"
        },
        {
            "id": "100067124820668",
            "count": 0,
            "name": "Ng퀋敲렬 d칯ng facebook"
        },
        {
            "id": "100067729713825",
            "count": 0,
            "name": "Ng퀋敲렬 d칯ng facebook"
        },
        {
            "id": "100067803637752",
            "count": 0,
            "name": "Ng퀋敲렬 d칯ng facebook"
        },
        {
            "id": "100067839890353",
            "count": 0,
            "name": "Ng퀋敲렬 d칯ng facebook"
        },
        {
            "id": "100068478576359",
            "count": 0,
            "name": "Ng퀋敲렬 d칯ng facebook"
        },
        {
            "id": "100068817998875",
            "count": 0,
            "name": "Ng퀋敲렬 d칯ng facebook"
        },
        {
            "id": "100069764767683",
            "count": 0,
            "name": "Ng퀋敲렬 d칯ng facebook"
        },
        {
            "id": "100070013348463",
            "count": 0,
            "name": "Ng퀋敲렬 d칯ng facebook"
        },
        {
            "id": "100070104925304",
            "count": 0,
            "name": "Ng퀋敲렬 d칯ng facebook"
        },
        {
            "id": "100070899521002",
            "count": 0,
            "name": "Ng퀋敲렬 d칯ng facebook"
        },
        {
            "id": "100071303594615",
            "count": 0,
            "name": "Ng퀋敲렬 d칯ng facebook"
        },
        {
            "id": "100071627507465",
            "count": 0,
            "name": "Ng퀋敲렬 d칯ng facebook"
        },
        {
            "id": "100072034345452",
            "count": 0,
            "name": "Ng퀋敲렬 d칯ng facebook"
        },
        {
            "id": "100072548933925",
            "count": 0,
            "name": "Ng퀋敲렬 d칯ng facebook"
        },
        {
            "id": "100072883089785",
            "count": 0,
            "name": "Ng퀋敲렬 d칯ng facebook"
        },
        {
            "id": "100072934636127",
            "count": 0,
            "name": "Ng퀋敲렬 d칯ng facebook"
        },
        {
            "id": "100073127936844",
            "count": 0,
            "name": "Ng퀋敲렬 d칯ng facebook"
        },
        {
            "id": "100073985167088",
            "count": 0,
            "name": "Ng퀋敲렬 d칯ng facebook"
        },
        {
            "id": "100074278195157",
            "count": 0,
            "name": "洧뉧눘洧눓洧눇 洧눈洧눘洧눜 洧눙洧눅 洧눒洧눌洧눘洧눒洧눋 洧눒洧눓洧눍 洧눆洧눘洧눓洧눒"
        },
        {
            "id": "100074341920164",
            "count": 0,
            "name": "Ng퀋敲렬 d칯ng facebook"
        },
        {
            "id": "100074524321875",
            "count": 0,
            "name": "Ng퀋敲렬 d칯ng facebook"
        },
        {
            "id": "100075980175339",
            "count": 0,
            "name": "Ng퀋敲렬 d칯ng facebook"
        },
        {
            "id": "100076399151586",
            "count": 0,
            "name": "Ng퀋敲렬 d칯ng facebook"
        },
        {
            "id": "100076975642630",
            "count": 0,
            "name": "Ng퀋敲렬 d칯ng facebook"
        },
        {
            "id": "100077509305730",
            "count": 0,
            "name": "Ng퀋敲렬 d칯ng facebook"
        },
        {
            "id": "100077597024757",
            "count": 0,
            "name": "Ng퀋敲렬 d칯ng facebook"
        },
        {
            "id": "100077639637264",
            "count": 0,
            "name": "Ng퀋敲렬 d칯ng facebook"
        },
        {
            "id": "100077971004043",
            "count": 0,
            "name": "Ng퀋敲렬 d칯ng facebook"
        },
        {
            "id": "100078681550289",
            "count": 0,
            "name": "Ng퀋敲렬 d칯ng facebook"
        },
        {
            "id": "100079130371607",
            "count": 0,
            "name": "Ng퀋敲렬 d칯ng facebook"
        },
        {
            "id": "100079876959448",
            "count": 0,
            "name": "Ng퀋敲렬 d칯ng facebook"
        },
        {
            "id": "100080804560507",
            "count": 0,
            "name": "Ng퀋敲렬 d칯ng facebook"
        },
        {
            "id": "100081002237761",
            "count": 0,
            "name": "Ng퀋敲렬 d칯ng facebook"
        },
        {
            "id": "100081206510186",
            "count": 0,
            "name": "Ng퀋敲렬 d칯ng facebook"
        },
        {
            "id": "100081443772674",
            "count": 0,
            "name": "Ng퀋敲렬 d칯ng facebook"
        },
        {
            "id": "100082552884338",
            "count": 0,
            "name": "Ng퀋敲렬 d칯ng facebook"
        },
        {
            "id": "100083022811644",
            "count": 0,
            "name": "Ng퀋敲렬 d칯ng facebook"
        },
        {
            "id": "100083504825451",
            "count": 0,
            "name": "Ng퀋敲렬 d칯ng facebook"
        },
        {
            "id": "100084012548620",
            "count": 0,
            "name": "Ng퀋敲렬 d칯ng facebook"
        },
        {
            "id": "100084071196298",
            "count": 0,
            "name": "Ng퀋敲렬 d칯ng facebook"
        },
        {
            "id": "100084235487772",
            "count": 0,
            "name": "Ng퀋敲렬 d칯ng facebook"
        },
        {
            "id": "100084459207826",
            "count": 0,
            "name": "Ng퀋敲렬 d칯ng facebook"
        },
        {
            "id": "100085264847000",
            "count": 0,
            "name": "Ng퀋敲렬 d칯ng facebook"
        },
        {
            "id": "100087223377781",
            "count": 0,
            "name": "Ng퀋敲렬 d칯ng facebook"
        },
        {
            "id": "100088003426784",
            "count": 0,
            "name": "Ng퀋敲렬 d칯ng facebook"
        },
        {
            "id": "100089669455408",
            "count": 0,
            "name": "Ng퀋敲렬 d칯ng facebook"
        },
        {
            "id": "100091841472833",
            "count": 0,
            "name": "Ng퀋敲렬 d칯ng facebook"
        },
        {
            "id": "100091847290662",
            "count": 0,
            "name": "Ng퀋敲렬 d칯ng facebook"
        },
        {
            "id": "100091905835858",
            "count": 0,
            "name": "Ng퀋敲렬 d칯ng facebook"
        },
        {
            "id": "100092011181468",
            "count": 0,
            "name": "Ng퀋敲렬 d칯ng facebook"
        },
        {
            "id": "100092203035367",
            "count": 0,
            "name": "Ng퀋敲렬 d칯ng facebook"
        },
        {
            "id": "100094046882331",
            "count": 0,
            "name": "Ng퀋敲렬 d칯ng facebook"
        },
        {
            "id": "100094262430488",
            "count": 0,
            "name": "Ng퀋敲렬 d칯ng facebook"
        },
        {
            "id": "100094326087158",
            "count": 0,
            "name": "Ng퀋敲렬 d칯ng facebook"
        },
        {
            "id": "100094365050149",
            "count": 0,
            "name": "Ng퀋敲렬 d칯ng facebook"
        },
        {
            "id": "100094496576944",
            "count": 0,
            "name": "Ng퀋敲렬 d칯ng facebook"
        },
        {
            "id": "100095080567117",
            "count": 0,
            "name": "Ng퀋敲렬 d칯ng facebook"
        },
        {
            "id": "100011620237069",
            "count": 0,
            "name": "Ng퀋敲렬 d칯ng facebook"
        },
        {
            "id": "100084174456709",
            "count": 0,
            "name": "Ng퀋敲렬 d칯ng facebook"
        },
        {
            "id": "100082529241487",
            "count": 0,
            "name": "Ng퀋敲렬 d칯ng facebook"
        },
        {
            "id": "100046043931686",
            "count": 0,
            "name": "Ng퀋敲렬 d칯ng facebook"
        },
        {
            "id": "100086997663423",
            "count": 0,
            "name": "Ng퀋敲렬 d칯ng facebook"
        },
        {
            "id": "100094285270891",
            "count": 0,
            "name": "Ng퀋敲렬 d칯ng facebook"
        },
        {
            "id": "100037712385256",
            "count": 0,
            "name": "Ng퀋敲렬 d칯ng facebook"
        },
        {
            "id": "100047759311760",
            "count": 0,
            "name": "Ng퀋敲렬 d칯ng facebook"
        },
        {
            "id": "100092716934305",
            "count": 0,
            "name": "Ng퀋敲렬 d칯ng facebook"
        },
        {
            "id": "100064106005769",
            "count": 0,
            "name": "Ng퀋敲렬 d칯ng facebook"
        },
        {
            "id": "100090737150315",
            "count": 0,
            "name": "Ng퀋敲렬 d칯ng facebook"
        },
        {
            "id": "100023390842520",
            "count": 0,
            "name": "Ng퀋敲렬 d칯ng facebook"
        },
        {
            "id": "100027933579703",
            "count": 0,
            "name": "Ng퀋敲렬 d칯ng facebook"
        },
        {
            "id": "100093250460325",
            "count": 0,
            "name": "Ng퀋敲렬 d칯ng facebook"
        },
        {
            "id": "100027377297534",
            "count": 0,
            "name": "Ng퀋敲렬 d칯ng facebook"
        },
        {
            "id": "100060560316441",
            "count": 0,
            "name": "Ng퀋敲렬 d칯ng facebook"
        },
        {
            "id": "61551633732896",
            "count": 0,
            "name": "Ng퀋敲렬 d칯ng facebook"
        },
        {
            "id": "100095425306290",
            "count": 0,
            "name": "Ng퀋敲렬 d칯ng facebook"
        },
        {
            "id": "100088486644888",
            "count": 0,
            "name": "Ng퀋敲렬 d칯ng facebook"
        }
    ],
    "day": [
        {
            "id": "61550591979493",
            "count": 0,
            "name": "Ng퀋敲렬 d칯ng facebook"
        },
        {
            "id": "61551750047010",
            "count": 0,
            "name": "Ng퀋敲렬 d칯ng facebook"
        },
        {
            "id": "61553301081985",
            "count": 0,
            "name": "Ng퀋敲렬 d칯ng facebook"
        },
        {
            "id": "100004843834867",
            "count": 0,
            "name": "Ng퀋敲렬 d칯ng Facebook"
        },
        {
            "id": "100007127623687",
            "count": 0,
            "name": "Ng퀋敲렬 d칯ng facebook"
        },
        {
            "id": "100009474414028",
            "count": 0,
            "name": "Ng퀋敲렬 d칯ng facebook"
        },
        {
            "id": "100011730017799",
            "count": 0,
            "name": "Ng퀋敲렬 d칯ng facebook"
        },
        {
            "id": "100013615989007",
            "count": 0,
            "name": "Ng퀋敲렬 d칯ng facebook"
        },
        {
            "id": "100014148825001",
            "count": 0,
            "name": "Ng퀋敲렬 d칯ng facebook"
        },
        {
            "id": "100019665720378",
            "count": 0,
            "name": "Ng퀋敲렬 d칯ng facebook"
        },
        {
            "id": "100022200258722",
            "count": 0,
            "name": "Ng퀋敲렬 d칯ng facebook"
        },
        {
            "id": "100022876771042",
            "count": 0,
            "name": "Ng퀋敲렬 d칯ng facebook"
        },
        {
            "id": "100024420073212",
            "count": 0,
            "name": "Ng퀋敲렬 d칯ng facebook"
        },
        {
            "id": "100025347006654",
            "count": 0,
            "name": "Ng퀋敲렬 d칯ng facebook"
        },
        {
            "id": "100029650151945",
            "count": 0,
            "name": "Ng퀋敲렬 d칯ng facebook"
        },
        {
            "id": "100030293616399",
            "count": 0,
            "name": "Ng퀋敲렬 d칯ng facebook"
        },
        {
            "id": "100030990391436",
            "count": 0,
            "name": "Ng퀋敲렬 d칯ng facebook"
        },
        {
            "id": "100031689702149",
            "count": 0,
            "name": "Ng퀋敲렬 d칯ng facebook"
        },
        {
            "id": "100034576779493",
            "count": 0,
            "name": "Ng퀋敲렬 d칯ng facebook"
        },
        {
            "id": "100034922898150",
            "count": 0,
            "name": "Ng퀋敲렬 d칯ng facebook"
        },
        {
            "id": "100035299548315",
            "count": 0,
            "name": "Ng퀋敲렬 d칯ng facebook"
        },
        {
            "id": "100037783553426",
            "count": 0,
            "name": "Ng퀋敲렬 d칯ng facebook"
        },
        {
            "id": "100038339124447",
            "count": 0,
            "name": "Ng퀋敲렬 d칯ng facebook"
        },
        {
            "id": "100039137588507",
            "count": 0,
            "name": "Ng퀋敲렬 d칯ng facebook"
        },
        {
            "id": "100040415021585",
            "count": 0,
            "name": "Ng퀋敲렬 d칯ng facebook"
        },
        {
            "id": "100041010338202",
            "count": 0,
            "name": "Ng퀋敲렬 d칯ng facebook"
        },
        {
            "id": "100041163427907",
            "count": 0,
            "name": "Ng퀋敲렬 d칯ng facebook"
        },
        {
            "id": "100041447961345",
            "count": 0,
            "name": "Ng퀋敲렬 d칯ng facebook"
        },
        {
            "id": "100045475484543",
            "count": 0,
            "name": "Ng퀋敲렬 d칯ng facebook"
        },
        {
            "id": "100046384474794",
            "count": 0,
            "name": "P. Hi故쯧"
        },
        {
            "id": "100049908011793",
            "count": 0,
            "name": "Ng퀋敲렬 d칯ng facebook"
        },
        {
            "id": "100049952270280",
            "count": 0,
            "name": "Ng퀋敲렬 d칯ng facebook"
        },
        {
            "id": "100050444104881",
            "count": 0,
            "name": "Ng퀋敲렬 d칯ng facebook"
        },
        {
            "id": "100050985814465",
            "count": 0,
            "name": "Ng퀋敲렬 d칯ng facebook"
        },
        {
            "id": "100053388225103",
            "count": 0,
            "name": "Ng퀋敲렬 d칯ng facebook"
        },
        {
            "id": "100053713476328",
            "count": 0,
            "name": "Ng퀋敲렬 d칯ng facebook"
        },
        {
            "id": "100054260715984",
            "count": 0,
            "name": "Ng퀋敲렬 d칯ng facebook"
        },
        {
            "id": "100054591240240",
            "count": 0,
            "name": "Ng퀋敲렬 d칯ng facebook"
        },
        {
            "id": "100055154154050",
            "count": 0,
            "name": "V칫 N-캠캒ng"
        },
        {
            "id": "100057164243839",
            "count": 0,
            "name": "Ng퀋敲렬 d칯ng facebook"
        },
        {
            "id": "100059650390794",
            "count": 0,
            "name": "Ng퀋敲렬 d칯ng facebook"
        },
        {
            "id": "100061609086598",
            "count": 0,
            "name": "Ng퀋敲렬 d칯ng facebook"
        },
        {
            "id": "100062257991835",
            "count": 0,
            "name": "Ng퀋敲렬 d칯ng facebook"
        },
        {
            "id": "100063330711799",
            "count": 0,
            "name": "Ng퀋敲렬 d칯ng facebook"
        },
        {
            "id": "100063637074188",
            "count": 0,
            "name": "Ng퀋敲렬 d칯ng facebook"
        },
        {
            "id": "100063708825168",
            "count": 0,
            "name": "Ng퀋敲렬 d칯ng facebook"
        },
        {
            "id": "100066662293438",
            "count": 0,
            "name": "Ng퀋敲렬 d칯ng facebook"
        },
        {
            "id": "100067124820668",
            "count": 0,
            "name": "Ng퀋敲렬 d칯ng facebook"
        },
        {
            "id": "100067729713825",
            "count": 0,
            "name": "Ng퀋敲렬 d칯ng facebook"
        },
        {
            "id": "100067803637752",
            "count": 0,
            "name": "Ng퀋敲렬 d칯ng facebook"
        },
        {
            "id": "100067839890353",
            "count": 0,
            "name": "Ng퀋敲렬 d칯ng facebook"
        },
        {
            "id": "100068478576359",
            "count": 0,
            "name": "Ng퀋敲렬 d칯ng facebook"
        },
        {
            "id": "100068817998875",
            "count": 0,
            "name": "Ng퀋敲렬 d칯ng facebook"
        },
        {
            "id": "100069764767683",
            "count": 0,
            "name": "Ng퀋敲렬 d칯ng facebook"
        },
        {
            "id": "100070013348463",
            "count": 0,
            "name": "Ng퀋敲렬 d칯ng facebook"
        },
        {
            "id": "100070104925304",
            "count": 0,
            "name": "Ng퀋敲렬 d칯ng facebook"
        },
        {
            "id": "100070899521002",
            "count": 0,
            "name": "Ng퀋敲렬 d칯ng facebook"
        },
        {
            "id": "100071303594615",
            "count": 0,
            "name": "Ng퀋敲렬 d칯ng facebook"
        },
        {
            "id": "100071627507465",
            "count": 0,
            "name": "Ng퀋敲렬 d칯ng facebook"
        },
        {
            "id": "100072034345452",
            "count": 0,
            "name": "Ng퀋敲렬 d칯ng facebook"
        },
        {
            "id": "100072548933925",
            "count": 0,
            "name": "Ng퀋敲렬 d칯ng facebook"
        },
        {
            "id": "100072883089785",
            "count": 0,
            "name": "Ng퀋敲렬 d칯ng facebook"
        },
        {
            "id": "100072934636127",
            "count": 0,
            "name": "Ng퀋敲렬 d칯ng facebook"
        },
        {
            "id": "100073127936844",
            "count": 0,
            "name": "Ng퀋敲렬 d칯ng facebook"
        },
        {
            "id": "100073985167088",
            "count": 0,
            "name": "Ng퀋敲렬 d칯ng facebook"
        },
        {
            "id": "100074278195157",
            "count": 0,
            "name": "洧뉧눘洧눓洧눇 洧눈洧눘洧눜 洧눙洧눅 洧눒洧눌洧눘洧눒洧눋 洧눒洧눓洧눍 洧눆洧눘洧눓洧눒"
        },
        {
            "id": "100074341920164",
            "count": 0,
            "name": "Ng퀋敲렬 d칯ng facebook"
        },
        {
            "id": "100074524321875",
            "count": 0,
            "name": "Ng퀋敲렬 d칯ng facebook"
        },
        {
            "id": "100075980175339",
            "count": 0,
            "name": "Ng퀋敲렬 d칯ng facebook"
        },
        {
            "id": "100076399151586",
            "count": 0,
            "name": "Ng퀋敲렬 d칯ng facebook"
        },
        {
            "id": "100076975642630",
            "count": 0,
            "name": "Ng퀋敲렬 d칯ng facebook"
        },
        {
            "id": "100077509305730",
            "count": 0,
            "name": "Ng퀋敲렬 d칯ng facebook"
        },
        {
            "id": "100077597024757",
            "count": 0,
            "name": "Ng퀋敲렬 d칯ng facebook"
        },
        {
            "id": "100077639637264",
            "count": 0,
            "name": "Ng퀋敲렬 d칯ng facebook"
        },
        {
            "id": "100077971004043",
            "count": 0,
            "name": "Ng퀋敲렬 d칯ng facebook"
        },
        {
            "id": "100078681550289",
            "count": 0,
            "name": "Ng퀋敲렬 d칯ng facebook"
        },
        {
            "id": "100079130371607",
            "count": 0,
            "name": "Ng퀋敲렬 d칯ng facebook"
        },
        {
            "id": "100079876959448",
            "count": 0,
            "name": "Ng퀋敲렬 d칯ng facebook"
        },
        {
            "id": "100080804560507",
            "count": 0,
            "name": "Ng퀋敲렬 d칯ng facebook"
        },
        {
            "id": "100081002237761",
            "count": 0,
            "name": "Ng퀋敲렬 d칯ng facebook"
        },
        {
            "id": "100081206510186",
            "count": 0,
            "name": "Ng퀋敲렬 d칯ng facebook"
        },
        {
            "id": "100081443772674",
            "count": 0,
            "name": "Ng퀋敲렬 d칯ng facebook"
        },
        {
            "id": "100082552884338",
            "count": 0,
            "name": "Ng퀋敲렬 d칯ng facebook"
        },
        {
            "id": "100083022811644",
            "count": 0,
            "name": "Ng퀋敲렬 d칯ng facebook"
        },
        {
            "id": "100083504825451",
            "count": 0,
            "name": "Ng퀋敲렬 d칯ng facebook"
        },
        {
            "id": "100084012548620",
            "count": 0,
            "name": "Ng퀋敲렬 d칯ng facebook"
        },
        {
            "id": "100084071196298",
            "count": 0,
            "name": "Ng퀋敲렬 d칯ng facebook"
        },
        {
            "id": "100084235487772",
            "count": 0,
            "name": "Ng퀋敲렬 d칯ng facebook"
        },
        {
            "id": "100084459207826",
            "count": 0,
            "name": "Ng퀋敲렬 d칯ng facebook"
        },
        {
            "id": "100085264847000",
            "count": 0,
            "name": "Ng퀋敲렬 d칯ng facebook"
        },
        {
            "id": "100087223377781",
            "count": 0,
            "name": "Ng퀋敲렬 d칯ng facebook"
        },
        {
            "id": "100088003426784",
            "count": 0,
            "name": "Ng퀋敲렬 d칯ng facebook"
        },
        {
            "id": "100089669455408",
            "count": 0,
            "name": "Ng퀋敲렬 d칯ng facebook"
        },
        {
            "id": "100091841472833",
            "count": 0,
            "name": "Ng퀋敲렬 d칯ng facebook"
        },
        {
            "id": "100091847290662",
            "count": 0,
            "name": "Ng퀋敲렬 d칯ng facebook"
        },
        {
            "id": "100091905835858",
            "count": 0,
            "name": "Ng퀋敲렬 d칯ng facebook"
        },
        {
            "id": "100092011181468",
            "count": 0,
            "name": "Ng퀋敲렬 d칯ng facebook"
        },
        {
            "id": "100092203035367",
            "count": 0,
            "name": "Ng퀋敲렬 d칯ng facebook"
        },
        {
            "id": "100094046882331",
            "count": 0,
            "name": "Ng퀋敲렬 d칯ng facebook"
        },
        {
            "id": "100094262430488",
            "count": 0,
            "name": "Ng퀋敲렬 d칯ng facebook"
        },
        {
            "id": "100094326087158",
            "count": 0,
            "name": "Ng퀋敲렬 d칯ng facebook"
        },
        {
            "id": "100094365050149",
            "count": 0,
            "name": "Ng퀋敲렬 d칯ng facebook"
        },
        {
            "id": "100094496576944",
            "count": 0,
            "name": "Ng퀋敲렬 d칯ng facebook"
        },
        {
            "id": "100095080567117",
            "count": 0,
            "name": "Ng퀋敲렬 d칯ng facebook"
        },
        {
            "id": "100011620237069",
            "count": 0,
            "name": "Ng퀋敲렬 d칯ng facebook"
        },
        {
            "id": "100084174456709",
            "count": 0,
            "name": "Ng퀋敲렬 d칯ng facebook"
        },
        {
            "id": "100082529241487",
            "count": 0,
            "name": "Ng퀋敲렬 d칯ng facebook"
        },
        {
            "id": "100046043931686",
            "count": 0,
            "name": "Ng퀋敲렬 d칯ng facebook"
        },
        {
            "id": "100086997663423",
            "count": 0,
            "name": "Ng퀋敲렬 d칯ng facebook"
        },
        {
            "id": "100094285270891",
            "count": 0,
            "name": "Ng퀋敲렬 d칯ng facebook"
        },
        {
            "id": "100037712385256",
            "count": 0,
            "name": "Ng퀋敲렬 d칯ng facebook"
        },
        {
            "id": "100047759311760",
            "count": 0,
            "name": "Ng퀋敲렬 d칯ng facebook"
        },
        {
            "id": "100092716934305",
            "count": 0,
            "name": "Ng퀋敲렬 d칯ng facebook"
        },
        {
            "id": "100064106005769",
            "count": 0,
            "name": "Ng퀋敲렬 d칯ng facebook"
        },
        {
            "id": "100090737150315",
            "count": 0,
            "name": "Ng퀋敲렬 d칯ng facebook"
        },
        {
            "id": "100023390842520",
            "count": 0,
            "name": "Ng퀋敲렬 d칯ng facebook"
        },
        {
            "id": "100027933579703",
            "count": 0,
            "name": "Ng퀋敲렬 d칯ng facebook"
        },
        {
            "id": "100093250460325",
            "count": 0,
            "name": "Ng퀋敲렬 d칯ng facebook"
        },
        {
            "id": "100027377297534",
            "count": 0,
            "name": "Ng퀋敲렬 d칯ng facebook"
        },
        {
            "id": "100060560316441",
            "count": 0,
            "name": "Ng퀋敲렬 d칯ng facebook"
        },
        {
            "id": "61551633732896",
            "count": 0,
            "name": "Ng퀋敲렬 d칯ng facebook"
        },
        {
            "id": "100095425306290",
            "count": 0,
            "name": "Ng퀋敲렬 d칯ng facebook"
        },
        {
            "id": "100088486644888",
            "count": 0,
            "name": "Ng퀋敲렬 d칯ng facebook"
        }
    ],
    "time": 3
}