{
    "total": [
        {
            "id": "100074278195157",
            "count": 1
        },
        {
            "id": "100002813808429",
            "count": 3
        },
        {
            "id": "100094884761715",
            "count": 0
        }
    ],
    "week": [
        {
            "id": "100074278195157",
            "count": 1
        },
        {
            "id": "100002813808429",
            "count": 3
        },
        {
            "id": "100094884761715",
            "count": 0
        }
    ],
    "day": [
        {
            "id": "100074278195157",
            "count": 1
        },
        {
            "id": "100002813808429",
            "count": 3
        },
        {
            "id": "100094884761715",
            "count": 0
        }
    ],
    "time": 3,
    "last": {
        "time": 0,
        "day": [
            {
                "id": "100074278195157",
                "count": 0
            },
            {
                "id": "100002813808429",
                "count": 0
            },
            {
                "id": "100094884761715",
                "count": 0
            }
        ],
        "week": [
            {
                "id": "100074278195157",
                "count": 0
            },
            {
                "id": "100002813808429",
                "count": 0
            },
            {
                "id": "100094884761715",
                "count": 0
            }
        ]
    }
}